{"kind":"Article","sha256":"e831f25c561b1d0ca9b660b6550564f4103e93ecf05b212320e189a2cca70a48","slug":"opensarlab-accounts","location":"/user-guides/opensarlab_accounts.md","dependencies":[],"frontmatter":{"title":"OpenSARLab Accounts","content_includes_title":false,"authors":[{"nameParsed":{"literal":"The ASF Services Team","given":"The ASF Services","family":"Team"},"name":"The ASF Services Team","id":"contributors-myst-generated-uid-0"}],"github":"https://github.com/ASFOpenSARlab/opensarlab-docs","numbering":{"title":{"offset":2}},"edit_url":"https://github.com/ASFOpenSARlab/opensarlab-docs/blob/dev/docs/user-guides/opensarlab_accounts.md","exports":[{"format":"md","filename":"opensarlab_accounts.md","url":"/opensarlab_accounts-a2c01420d8572c49333634f6f7dd458d.md"}]},"mdast":{"type":"root","children":[{"type":"block","children":[{"type":"break","key":"WYG9Ta0Xb6"},{"type":"paragraph","position":{"start":{"line":4,"column":1},"end":{"line":4,"column":1}},"children":[{"type":"text","value":"OpenSARLab is a cloud-hosted JupyterHub configured for working with SAR data. It is deployed next to NASA data in AWS region us-west-2 for low-latency access to large SAR datasets.","position":{"start":{"line":4,"column":1},"end":{"line":4,"column":1}},"key":"wnFzwua4Bd"}],"key":"MMHtRefIIa"},{"type":"list","ordered":false,"spread":false,"position":{"start":{"line":7,"column":1},"end":{"line":10,"column":1}},"children":[{"type":"listItem","spread":true,"position":{"start":{"line":7,"column":1},"end":{"line":7,"column":1}},"children":[{"type":"crossReference","position":{"start":{"line":7,"column":1},"end":{"line":7,"column":1}},"children":[{"type":"text","value":"Access to OpenSARLab","position":{"start":{"line":7,"column":1},"end":{"line":7,"column":1}},"key":"fghK6o7B5V"}],"identifier":"access-to-opensarlab","label":"Access-to-OpenSARLab","kind":"heading","template":"{name}","resolved":true,"html_id":"access-to-opensarlab","key":"Qq1rTYnuwv"}],"key":"NoCIZfLlpE"},{"type":"listItem","spread":true,"position":{"start":{"line":8,"column":1},"end":{"line":8,"column":1}},"children":[{"type":"crossReference","position":{"start":{"line":8,"column":1},"end":{"line":8,"column":1}},"children":[{"type":"text","value":"Account Lifecycle","position":{"start":{"line":8,"column":1},"end":{"line":8,"column":1}},"key":"ZHCrB1uQgU"}],"identifier":"account-lifecycle","label":"Account-Lifecycle","kind":"heading","template":"{name}","resolved":true,"html_id":"account-lifecycle","key":"nN8qi91sGt"}],"key":"CkmTY16Die"},{"type":"listItem","spread":true,"position":{"start":{"line":9,"column":1},"end":{"line":10,"column":1}},"children":[{"type":"crossReference","position":{"start":{"line":9,"column":1},"end":{"line":9,"column":1}},"children":[{"type":"text","value":"OpenSARLab Environment","position":{"start":{"line":9,"column":1},"end":{"line":9,"column":1}},"key":"r2yj3waHwj"}],"identifier":"opensarlab-environment","label":"OpenSARLab-Environment","kind":"heading","template":"{name}","resolved":true,"html_id":"opensarlab-environment","key":"THvKO2F33Q"}],"key":"EgYOWcrlZY"}],"key":"ZcGWUWlDxh"},{"type":"thematicBreak","position":{"start":{"line":11,"column":1},"end":{"line":11,"column":1}},"key":"jONZu6U3NT"},{"type":"heading","depth":2,"position":{"start":{"line":14,"column":1},"end":{"line":14,"column":1}},"children":[{"type":"text","value":"Access to OpenSARLab","position":{"start":{"line":14,"column":1},"end":{"line":14,"column":1}},"key":"V85VJQ3STf"}],"label":"Access-to-OpenSARLab","identifier":"access-to-opensarlab","html_id":"access-to-opensarlab","key":"uEtO2jnpCg"},{"type":"paragraph","position":{"start":{"line":16,"column":1},"end":{"line":16,"column":1}},"children":[{"type":"text","value":"ASF provides limited access to OpenSARLab.","position":{"start":{"line":16,"column":1},"end":{"line":16,"column":1}},"key":"cwWu4YxQVh"}],"key":"QvkV7j705y"},{"type":"list","ordered":false,"spread":false,"position":{"start":{"line":17,"column":1},"end":{"line":19,"column":1}},"children":[{"type":"listItem","spread":true,"position":{"start":{"line":17,"column":1},"end":{"line":17,"column":1}},"children":[{"type":"text","value":"NASA-affiliates are granted access upon ","position":{"start":{"line":17,"column":1},"end":{"line":17,"column":1}},"key":"EGmwVoypzL"},{"type":"link","url":"mailto:uso@asf.alaska.edu?subject=NASA-affiliate%20OSL%20access%20request","position":{"start":{"line":17,"column":1},"end":{"line":17,"column":1}},"children":[{"type":"text","value":"request","position":{"start":{"line":17,"column":1},"end":{"line":17,"column":1}},"key":"l5uM1sXT8N"}],"urlSource":"mailto:uso@asf.alaska.edu?subject=NASA-affiliate%20OSL%20access%20request","key":"k8WAIl6oVz"},{"type":"text","value":".","position":{"start":{"line":17,"column":1},"end":{"line":17,"column":1}},"key":"kyT9BCAP8I"}],"key":"xjciBxmcII"},{"type":"listItem","spread":true,"position":{"start":{"line":18,"column":1},"end":{"line":19,"column":1}},"children":[{"type":"text","value":"All others may apply for access by completing the ","position":{"start":{"line":18,"column":1},"end":{"line":18,"column":1}},"key":"HeJDSQKkvl"},{"type":"link","url":"https://forms.gle/LNBCwe8JohYitvfy6","position":{"start":{"line":18,"column":1},"end":{"line":18,"column":1}},"children":[{"type":"text","value":"OpenSARLab Access Application","position":{"start":{"line":18,"column":1},"end":{"line":18,"column":1}},"key":"hdJuhpfYLF"}],"urlSource":"https://forms.gle/LNBCwe8JohYitvfy6","key":"qx8dYC5shE"},{"type":"text","value":".","position":{"start":{"line":18,"column":1},"end":{"line":18,"column":1}},"key":"X1vIEXhmHJ"}],"key":"fzBDss26RH"}],"key":"NZ5OiQ05fR"},{"type":"details","children":[{"type":"summary","children":[{"type":"link","url":"https://forms.gle/LNBCwe8JohYitvfy6","position":{"start":{"line":20,"column":1},"end":{"line":20,"column":1}},"children":[{"type":"text","value":"OpenSARLab Access Application","position":{"start":{"line":20,"column":1},"end":{"line":20,"column":1}},"key":"T5RtqCAMK5"}],"urlSource":"https://forms.gle/LNBCwe8JohYitvfy6","key":"rcvCvuy28A"}],"key":"NGGApcknBl"},{"type":"iframe","src":"https://forms.gle/LNBCwe8JohYitvfy6","key":"sBL5zmjT6p"}],"key":"pGIJ3o9Lep"},{"type":"thematicBreak","position":{"start":{"line":24,"column":1},"end":{"line":24,"column":1}},"key":"OuwOIc5ZJD"},{"type":"heading","depth":2,"position":{"start":{"line":26,"column":1},"end":{"line":26,"column":1}},"children":[{"type":"text","value":"Account Lifecycle","position":{"start":{"line":26,"column":1},"end":{"line":26,"column":1}},"key":"oUngxRSqyN"}],"label":"Account-Lifecycle","identifier":"account-lifecycle","html_id":"account-lifecycle","key":"iNniyycfSi"},{"type":"list","ordered":false,"spread":false,"position":{"start":{"line":27,"column":1},"end":{"line":30,"column":1}},"children":[{"type":"listItem","spread":true,"position":{"start":{"line":27,"column":1},"end":{"line":27,"column":1}},"children":[{"type":"text","value":"Accounts will be deactivated on the ","position":{"start":{"line":27,"column":1},"end":{"line":27,"column":1}},"key":"sc1q16sSHS"},{"type":"strong","position":{"start":{"line":27,"column":1},"end":{"line":27,"column":1}},"children":[{"type":"text","value":"30th","position":{"start":{"line":27,"column":1},"end":{"line":27,"column":1}},"key":"vLWLgY3NkV"}],"key":"zLNiJnciNa"},{"type":"text","value":" day of inactivity.","position":{"start":{"line":27,"column":1},"end":{"line":27,"column":1}},"key":"kB41ibAEFj"}],"key":"rBTQVJontE"},{"type":"listItem","spread":true,"position":{"start":{"line":28,"column":1},"end":{"line":28,"column":1}},"children":[{"type":"text","value":"Warning emails are sent to inactive users after ","position":{"start":{"line":28,"column":1},"end":{"line":28,"column":1}},"key":"RtmnZycN83"},{"type":"strong","position":{"start":{"line":28,"column":1},"end":{"line":28,"column":1}},"children":[{"type":"text","value":"29","position":{"start":{"line":28,"column":1},"end":{"line":28,"column":1}},"key":"VsciuulptH"}],"key":"HFJFM8YAaK"},{"type":"text","value":", ","position":{"start":{"line":28,"column":1},"end":{"line":28,"column":1}},"key":"OKsEVunkvE"},{"type":"strong","position":{"start":{"line":28,"column":1},"end":{"line":28,"column":1}},"children":[{"type":"text","value":"27","position":{"start":{"line":28,"column":1},"end":{"line":28,"column":1}},"key":"AlN9ekIzEs"}],"key":"XawRIYtx0z"},{"type":"text","value":", and ","position":{"start":{"line":28,"column":1},"end":{"line":28,"column":1}},"key":"ba86fY6gvA"},{"type":"strong","position":{"start":{"line":28,"column":1},"end":{"line":28,"column":1}},"children":[{"type":"text","value":"24","position":{"start":{"line":28,"column":1},"end":{"line":28,"column":1}},"key":"qP2so7if0X"}],"key":"AZWKbU72hI"},{"type":"text","value":" days.","position":{"start":{"line":28,"column":1},"end":{"line":28,"column":1}},"key":"iZDoFVUEpB"}],"key":"jOktJVHlsa"},{"type":"listItem","spread":true,"position":{"start":{"line":29,"column":1},"end":{"line":30,"column":1}},"children":[{"type":"text","value":"The user volume and snapshot are ","position":{"start":{"line":29,"column":1},"end":{"line":29,"column":1}},"key":"FbuXAXoCbB"},{"type":"strong","position":{"start":{"line":29,"column":1},"end":{"line":29,"column":1}},"children":[{"type":"text","value":"permanently destroyed","position":{"start":{"line":29,"column":1},"end":{"line":29,"column":1}},"key":"isVLssgEsL"}],"key":"DVhFWegeF4"},{"type":"text","value":" upon account deactivation.","position":{"start":{"line":29,"column":1},"end":{"line":29,"column":1}},"key":"GFcYIxjMzF"}],"key":"lQbxJqSzvw"}],"key":"sl6KtlIga1"},{"type":"paragraph","position":{"start":{"line":31,"column":1},"end":{"line":31,"column":1}},"children":[{"type":"emphasis","position":{"start":{"line":31,"column":1},"end":{"line":31,"column":1}},"children":[{"type":"text","value":"Lifecycle periods for custom labs may differ.","position":{"start":{"line":31,"column":1},"end":{"line":31,"column":1}},"key":"iAq1AJKWCC"}],"key":"IKxcga8HUG"}],"key":"ysqxfPxYNK"},{"type":"thematicBreak","position":{"start":{"line":33,"column":1},"end":{"line":33,"column":1}},"key":"eFoYOMq3fK"},{"type":"heading","depth":2,"position":{"start":{"line":36,"column":1},"end":{"line":36,"column":1}},"children":[{"type":"text","value":"OpenSARLab Environment","position":{"start":{"line":36,"column":1},"end":{"line":36,"column":1}},"key":"Hh6zX6jXht"}],"label":"OpenSARLab-Environment","identifier":"opensarlab-environment","html_id":"opensarlab-environment","key":"FrMK8oBhV8"},{"type":"heading","depth":3,"position":{"start":{"line":38,"column":1},"end":{"line":38,"column":1}},"children":[{"type":"text","value":"Operating System","position":{"start":{"line":38,"column":1},"end":{"line":38,"column":1}},"key":"fciDkD8pdL"}],"identifier":"operating-system","label":"Operating System","html_id":"operating-system","implicit":true,"key":"b5clvx9G5r"},{"type":"list","ordered":false,"spread":false,"position":{"start":{"line":40,"column":1},"end":{"line":41,"column":1}},"children":[{"type":"listItem","spread":true,"position":{"start":{"line":40,"column":1},"end":{"line":41,"column":1}},"children":[{"type":"text","value":"Ubuntu 22.04.4 LTS","position":{"start":{"line":40,"column":1},"end":{"line":40,"column":1}},"key":"PAFClyw0gT"}],"key":"eoSNtn69SA"}],"key":"QP0l7TZsLc"},{"type":"heading","depth":3,"position":{"start":{"line":42,"column":1},"end":{"line":42,"column":1}},"children":[{"type":"text","value":"Server Profiles","position":{"start":{"line":42,"column":1},"end":{"line":42,"column":1}},"key":"PpQxqDQaev"}],"identifier":"server-profiles","label":"Server Profiles","html_id":"server-profiles","implicit":true,"key":"BlF734WKhc"},{"type":"paragraph","position":{"start":{"line":43,"column":1},"end":{"line":43,"column":1}},"children":[{"type":"text","value":"Every OpenSARLab user has access to a JupyterHub server running on an AWS EC2 instance. Users may select from two server profiles offering varying amounts of compute resources to support different workloads.","position":{"start":{"line":43,"column":1},"end":{"line":43,"column":1}},"key":"iE4iFfeHzK"}],"key":"wAkQSJmyPa"},{"type":"blockquote","position":{"start":{"line":44,"column":1},"end":{"line":52,"column":1}},"children":[{"type":"paragraph","position":{"start":{"line":44,"column":1},"end":{"line":44,"column":1}},"children":[{"type":"strong","position":{"start":{"line":44,"column":1},"end":{"line":44,"column":1}},"children":[{"type":"text","value":"m6a.large:","position":{"start":{"line":44,"column":1},"end":{"line":44,"column":1}},"key":"SP8NCu4v9h"}],"key":"wxqG5DxdpB"}],"key":"D8x19Hs2It"},{"type":"list","ordered":false,"spread":false,"position":{"start":{"line":45,"column":1},"end":{"line":48,"column":1}},"children":[{"type":"listItem","spread":true,"position":{"start":{"line":45,"column":1},"end":{"line":45,"column":1}},"children":[{"type":"text","value":"RAM Guarantee: 5G","position":{"start":{"line":45,"column":1},"end":{"line":45,"column":1}},"key":"VGYCuqdrRf"}],"key":"IizmYcXNJY"},{"type":"listItem","spread":true,"position":{"start":{"line":46,"column":1},"end":{"line":46,"column":1}},"children":[{"type":"text","value":"RAM limit: 8G","position":{"start":{"line":46,"column":1},"end":{"line":46,"column":1}},"key":"uJEnip7mzj"}],"key":"B2fga78KDX"},{"type":"listItem","spread":true,"position":{"start":{"line":47,"column":1},"end":{"line":48,"column":1}},"children":[{"type":"text","value":"CPU limit: 2","position":{"start":{"line":47,"column":1},"end":{"line":47,"column":1}},"key":"kFTkaxZgbD"}],"key":"Vh4laj0PlJ"}],"key":"hfvcTydmzT"},{"type":"paragraph","position":{"start":{"line":49,"column":1},"end":{"line":49,"column":1}},"children":[{"type":"strong","position":{"start":{"line":49,"column":1},"end":{"line":49,"column":1}},"children":[{"type":"text","value":"m6a.xlarge:","position":{"start":{"line":49,"column":1},"end":{"line":49,"column":1}},"key":"w1BzrYdZj8"}],"key":"hdiCVup2co"}],"key":"u7UohRnpWR"},{"type":"list","ordered":false,"spread":false,"position":{"start":{"line":50,"column":1},"end":{"line":52,"column":1}},"children":[{"type":"listItem","spread":true,"position":{"start":{"line":50,"column":1},"end":{"line":50,"column":1}},"children":[{"type":"text","value":"RAM Guarantee: 10G","position":{"start":{"line":50,"column":1},"end":{"line":50,"column":1}},"key":"vjdZ9tgntQ"}],"key":"pEGv0ZNRo1"},{"type":"listItem","spread":true,"position":{"start":{"line":51,"column":1},"end":{"line":51,"column":1}},"children":[{"type":"text","value":"RAM limit: 16G","position":{"start":{"line":51,"column":1},"end":{"line":51,"column":1}},"key":"NmarBRuiXX"}],"key":"VnQcc25eEJ"},{"type":"listItem","spread":true,"position":{"start":{"line":52,"column":1},"end":{"line":52,"column":1}},"children":[{"type":"text","value":"CPU limit: 4","position":{"start":{"line":52,"column":1},"end":{"line":52,"column":1}},"key":"WF5rB8XlPq"}],"key":"v4tX1752Y1"}],"key":"zGLuUiIU4a"}],"key":"PewbpYI4cM"},{"type":"heading","depth":3,"position":{"start":{"line":54,"column":1},"end":{"line":54,"column":1}},"children":[{"type":"text","value":"Volume (storage)","position":{"start":{"line":54,"column":1},"end":{"line":54,"column":1}},"key":"Iih1rkyKrQ"}],"identifier":"volume-storage","label":"Volume (storage)","html_id":"volume-storage","implicit":true,"key":"QGCvC6EhIL"},{"type":"list","ordered":false,"spread":false,"position":{"start":{"line":56,"column":1},"end":{"line":57,"column":1}},"children":[{"type":"listItem","spread":true,"position":{"start":{"line":56,"column":1},"end":{"line":57,"column":1}},"children":[{"type":"text","value":"*500GB of EBS volume storage per user.","position":{"start":{"line":56,"column":1},"end":{"line":56,"column":1}},"key":"R430DHwwP9"}],"key":"MpR6uy1Vz1"}],"key":"NSJoitdRj1"},{"type":"paragraph","position":{"start":{"line":58,"column":1},"end":{"line":58,"column":1}},"children":[{"type":"text","value":"OpenSARLab uses ","position":{"start":{"line":58,"column":1},"end":{"line":58,"column":1}},"key":"VgdaGuyD5r"},{"type":"link","url":"https://docs.aws.amazon.com/AWSEC2/latest/UserGuide/ebs-volumes.html","position":{"start":{"line":58,"column":1},"end":{"line":58,"column":1}},"children":[{"type":"text","value":"Amazon AWS EBS volumes","position":{"start":{"line":58,"column":1},"end":{"line":58,"column":1}},"key":"gvMdWEMH2x"}],"urlSource":"https://docs.aws.amazon.com/AWSEC2/latest/UserGuide/ebs-volumes.html","key":"LFbsJrtMVf"},{"type":"text","value":" mounted on user servers’ home directories for persistent storage.","position":{"start":{"line":58,"column":1},"end":{"line":58,"column":1}},"key":"NEgMku99yl"}],"key":"BjAdZN1oXV"},{"type":"list","ordered":false,"spread":false,"position":{"start":{"line":60,"column":1},"end":{"line":62,"column":1}},"children":[{"type":"listItem","spread":true,"position":{"start":{"line":60,"column":1},"end":{"line":62,"column":1}},"children":[{"type":"text","value":"If a volume is full when a user shuts down their server, it will trigger an ","position":{"start":{"line":60,"column":1},"end":{"line":60,"column":1}},"key":"enrrAyHOsL"},{"type":"inlineCode","value":"out-of-storage exception","position":{"start":{"line":60,"column":1},"end":{"line":60,"column":1}},"key":"C96B43FLcu"},{"type":"text","value":" that will prevent users from starting a server again.","position":{"start":{"line":60,"column":1},"end":{"line":60,"column":1}},"key":"C82nrQIh97"},{"type":"list","ordered":false,"spread":false,"position":{"start":{"line":61,"column":1},"end":{"line":62,"column":1}},"children":[{"type":"listItem","spread":true,"position":{"start":{"line":61,"column":1},"end":{"line":62,"column":1}},"children":[{"type":"text","value":"Please contact an ","position":{"start":{"line":61,"column":1},"end":{"line":61,"column":1}},"key":"gbeeIZXvMt"},{"type":"link","url":"mailto:uaf-jupyterhub-asf@alaska.edu","position":{"start":{"line":61,"column":1},"end":{"line":61,"column":1}},"children":[{"type":"text","value":"OpenScienceLab administrator","position":{"start":{"line":61,"column":1},"end":{"line":61,"column":1}},"key":"JBDKXJiQQF"}],"urlSource":"mailto:uaf-jupyterhub-asf@alaska.edu","key":"d0RGZAVZdP"},{"type":"text","value":" if this occurs.","position":{"start":{"line":61,"column":1},"end":{"line":61,"column":1}},"key":"Fnrqx2MRQw"}],"key":"or6w55g1I8"}],"key":"qdaKEOcwST"}],"key":"i6Slehhzdf"}],"key":"nLprZw4k7I"},{"type":"heading","depth":3,"position":{"start":{"line":63,"column":1},"end":{"line":63,"column":1}},"children":[{"type":"strong","position":{"start":{"line":63,"column":1},"end":{"line":63,"column":1}},"children":[{"type":"text","value":"Privileges","position":{"start":{"line":63,"column":1},"end":{"line":63,"column":1}},"key":"StIxD6aQLU"}],"key":"S7VrknBWTt"}],"identifier":"privileges","label":"Privileges","html_id":"privileges","implicit":true,"key":"Mu9TxBMRDs"},{"type":"list","ordered":false,"spread":false,"position":{"start":{"line":64,"column":1},"end":{"line":66,"column":1}},"children":[{"type":"listItem","spread":true,"position":{"start":{"line":64,"column":1},"end":{"line":64,"column":1}},"children":[{"type":"text","value":"Users do not have ","position":{"start":{"line":64,"column":1},"end":{"line":64,"column":1}},"key":"RJx0h7SjbJ"},{"type":"inlineCode","value":"root","position":{"start":{"line":64,"column":1},"end":{"line":64,"column":1}},"key":"k3LADcVaAu"},{"type":"text","value":" (i.e., ","position":{"start":{"line":64,"column":1},"end":{"line":64,"column":1}},"key":"zGGMC927ww"},{"type":"inlineCode","value":"sudo","position":{"start":{"line":64,"column":1},"end":{"line":64,"column":1}},"key":"Q6Njrf3NDE"},{"type":"text","value":") privileges.","position":{"start":{"line":64,"column":1},"end":{"line":64,"column":1}},"key":"CNPTmM80WD"}],"key":"jqhCcC2y6q"},{"type":"listItem","spread":true,"position":{"start":{"line":65,"column":1},"end":{"line":66,"column":1}},"children":[{"type":"text","value":"Users have read/write access in their local directories on their EBS volumes, but limited write access in their root directories.","position":{"start":{"line":65,"column":1},"end":{"line":65,"column":1}},"key":"kpjGVEFmRZ"}],"key":"Uc4lJYCGGb"}],"key":"EEM6L0gVX0"}],"key":"cPUyZKvvXh"}],"key":"FwTDZTDQ7e"},"references":{"cite":{"order":[],"data":{}}}}